odoo10_addon_l10n_es_aeat_sii-10.0.5.0.1-py3.8-nspkg.pth
odoo/addons/l10n_es_aeat_sii/README.rst
odoo/addons/l10n_es_aeat_sii/__init__.py
odoo/addons/l10n_es_aeat_sii/__manifest__.py
odoo/addons/l10n_es_aeat_sii/hooks.py
odoo/addons/l10n_es_aeat_sii/data/aeat_sii_map_data.xml
odoo/addons/l10n_es_aeat_sii/data/aeat_sii_mapping_registration_keys_data.xml
odoo/addons/l10n_es_aeat_sii/data/aeat_sii_tax_agency_data.xml
odoo/addons/l10n_es_aeat_sii/data/ir_config_parameter.xml
odoo/addons/l10n_es_aeat_sii/i18n/bg.po
odoo/addons/l10n_es_aeat_sii/i18n/ca.po
odoo/addons/l10n_es_aeat_sii/i18n/ca_ES.po
odoo/addons/l10n_es_aeat_sii/i18n/cs.po
odoo/addons/l10n_es_aeat_sii/i18n/de.po
odoo/addons/l10n_es_aeat_sii/i18n/es.po
odoo/addons/l10n_es_aeat_sii/i18n/es_CO.po
odoo/addons/l10n_es_aeat_sii/i18n/es_CR.po
odoo/addons/l10n_es_aeat_sii/i18n/es_ES.po
odoo/addons/l10n_es_aeat_sii/i18n/eu.po
odoo/addons/l10n_es_aeat_sii/i18n/fr.po
odoo/addons/l10n_es_aeat_sii/i18n/gl.po
odoo/addons/l10n_es_aeat_sii/i18n/hr.po
odoo/addons/l10n_es_aeat_sii/i18n/l10n_es_aeat_sii.pot
odoo/addons/l10n_es_aeat_sii/i18n/nl.po
odoo/addons/l10n_es_aeat_sii/i18n/pl.po
odoo/addons/l10n_es_aeat_sii/i18n/pt.po
odoo/addons/l10n_es_aeat_sii/i18n/pt_BR.po
odoo/addons/l10n_es_aeat_sii/i18n/ru.po
odoo/addons/l10n_es_aeat_sii/i18n/sl.po
odoo/addons/l10n_es_aeat_sii/i18n/sv.po
odoo/addons/l10n_es_aeat_sii/i18n/tr.po
odoo/addons/l10n_es_aeat_sii/i18n/vi.po
odoo/addons/l10n_es_aeat_sii/migrations/9.0.1.7.0/post-migration.py
odoo/addons/l10n_es_aeat_sii/models/__init__.py
odoo/addons/l10n_es_aeat_sii/models/account_fiscal_position.py
odoo/addons/l10n_es_aeat_sii/models/account_invoice.py
odoo/addons/l10n_es_aeat_sii/models/account_invoice_tax.py
odoo/addons/l10n_es_aeat_sii/models/aeat_sii.py
odoo/addons/l10n_es_aeat_sii/models/aeat_sii_map.py
odoo/addons/l10n_es_aeat_sii/models/aeat_sii_mapping_registration_keys.py
odoo/addons/l10n_es_aeat_sii/models/aeat_sii_tax_agency.py
odoo10_addon_l10n_es_aeat_sii-10.0.5.0.1.dist-info/METADATA
odoo10_addon_l10n_es_aeat_sii-10.0.5.0.1.dist-info/WHEEL
odoo10_addon_l10n_es_aeat_sii-10.0.5.0.1.dist-info/namespace_packages.txt
odoo10_addon_l10n_es_aeat_sii-10.0.5.0.1.dist-info/top_level.txt
odoo10_addon_l10n_es_aeat_sii-10.0.5.0.1.dist-info/RECORD
