Metadata-Version: 2.1
Name: odoo10-addon-l10n-es-aeat-sii
Version: 10.0.5.0.1
Summary: Suministro Inmediato de Información en el IVA
Home-page: https://odoospain.odoo.com
Author: Acysos S.L.,Diagram,Minorisa,Studio73,FactorLibre,Comunitea,Otherway,Tecnativa,Javi Melendez,Odoo Community Association (OCA)
Author-email: support@odoo-community.org
License: AGPL-3
Platform: UNKNOWN
Classifier: Programming Language :: Python
Classifier: Framework :: Odoo
Classifier: Framework :: Odoo :: 10.0
Classifier: License :: OSI Approved :: GNU Affero General Public License v3
Classifier: Development Status :: 5 - Production/Stable
Requires-Python: ~=2.7
Requires-Dist: odoo10-addon-account-invoice-refund-link
Requires-Dist: odoo10-addon-l10n-es-aeat
Requires-Dist: odoo10-addon-queue-job
Requires-Dist: odoo (<10.1dev,>=10.0)
Requires-Dist: pyOpenSSL (>=0.15)
Requires-Dist: requests
Requires-Dist: zeep
